github/AccessToken.py
github/AdvisoryBase.py
github/AdvisoryCredit.py
github/AdvisoryCreditDetailed.py
github/AdvisoryVulnerability.py
github/AdvisoryVulnerabilityPackage.py
github/AppAuthentication.py
github/ApplicationOAuth.py
github/Artifact.py
github/Auth.py
github/AuthenticatedUser.py
github/Authorization.py
github/AuthorizationApplication.py
github/Autolink.py
github/Branch.py
github/BranchProtection.py
github/CVSS.py
github/CWE.py
github/CheckRun.py
github/CheckRunAnnotation.py
github/CheckRunOutput.py
github/CheckSuite.py
github/Clones.py
github/CodeScanAlert.py
github/CodeScanAlertInstance.py
github/CodeScanAlertInstanceLocation.py
github/CodeScanRule.py
github/CodeScanTool.py
github/Commit.py
github/CommitCombinedStatus.py
github/CommitComment.py
github/CommitStats.py
github/CommitStatus.py
github/Comparison.py
github/Consts.py
github/ContentFile.py
github/DependabotAlert.py
github/DependabotAlertAdvisory.py
github/DependabotAlertDependency.py
github/DependabotAlertVulnerability.py
github/Deployment.py
github/DeploymentStatus.py
github/DiscussionBase.py
github/DiscussionCommentBase.py
github/Download.py
github/Enterprise.py
github/EnterpriseConsumedLicenses.py
github/Environment.py
github/EnvironmentDeploymentBranchPolicy.py
github/EnvironmentProtectionRule.py
github/EnvironmentProtectionRuleReviewer.py
github/Event.py
github/File.py
github/Gist.py
github/GistComment.py
github/GistFile.py
github/GistHistoryState.py
github/GitAuthor.py
github/GitBlob.py
github/GitCommit.py
github/GitObject.py
github/GitRef.py
github/GitRelease.py
github/GitReleaseAsset.py
github/GitTag.py
github/GitTree.py
github/GitTreeElement.py
github/GithubApp.py
github/GithubException.py
github/GithubIntegration.py
github/GithubObject.py
github/GithubRetry.py
github/GitignoreTemplate.py
github/GlobalAdvisory.py
github/Hook.py
github/HookDelivery.py
github/HookDescription.py
github/HookResponse.py
github/InputFileContent.py
github/InputGitAuthor.py
github/InputGitTreeElement.py
PyGithub-2.5.0.dist-info/COPYING
PyGithub-2.5.0.dist-info/COPYING.LESSER
PyGithub-2.5.0.dist-info/METADATA
PyGithub-2.5.0.dist-info/WHEEL
PyGithub-2.5.0.dist-info/top_level.txt
PyGithub-2.5.0.dist-info/RECORD
