Metadata-Version: 2.1
Name: PyGithub
Version: 2.5.0
Summary: Use the full Github API v3
Author-email: Vincent Jacques <vincent@vincent-jacques.net>
Project-URL: Documentation, https://pygithub.readthedocs.io/en/stable/
Project-URL: Source, https://github.com/pygithub/pygithub
Project-URL: Tracker, https://github.com/pygithub/pygithub/issues
Keywords: github
Classifier: Development Status :: 5 - Production/Stable
Classifier: Environment :: Web Environment
Classifier: Intended Audience :: Developers
Classifier: License :: OSI Approved :: GNU Library or Lesser General Public License (LGPL)
Classifier: Operating System :: OS Independent
Classifier: Programming Language :: Python
Classifier: Programming Language :: Python :: 3
Classifier: Programming Language :: Python :: 3.8
Classifier: Programming Language :: Python :: 3.9
Classifier: Programming Language :: Python :: 3.10
Classifier: Programming Language :: Python :: 3.11
Classifier: Programming Language :: Python :: 3.12
Classifier: Topic :: Software Development
Requires-Python: >=3.8
License-File: COPYING
License-File: COPYING.LESSER
Requires-Dist: pynacl>=1.4.0
Requires-Dist: requests>=2.14.0
Requires-Dist: pyjwt[crypto]>=2.4.0
Requires-Dist: typing-extensions>=4.0.0
Requires-Dist: urllib3>=1.26.0
Requires-Dist: Deprecated
Provides-Extra: integrations
